{"version":3,"kind":"Article","sha256":"8fe064c5924f150d29a2a896afe4b1bb0ef5dd2391e6fdde9b2b0ffc89987f00","slug":"index-4","location":"/content/txteditor/index.md","dependencies":[],"frontmatter":{"title":"Text Editor Git Configuration","content_includes_title":false,"authors":[{"nameParsed":{"literal":"Richard W. Evans","given":"Richard W.","family":"Evans"},"name":"Richard W. Evans","id":"contributors-myst-generated-uid-0"},{"nameParsed":{"literal":"Jason DeBacker","given":"Jason","family":"DeBacker"},"name":"Jason DeBacker","id":"contributors-myst-generated-uid-1"}],"github":"https://github.com/PSLmodels/Git-Tutorial","numbering":{"title":{"enabled":true}},"source_url":"https://github.com/PSLmodels/Git-Tutorial/blob/main/book/content/txteditor/index.md","edit_url":"https://github.com/PSLmodels/Git-Tutorial/edit/main/book/content/txteditor/index.md","enumerator":"4","exports":[{"format":"md","filename":"index.md","url":"/Git-Tutorial/build/index-43b14093f089c49896ac8ef2685c132d.md"}]},"mdast":{"type":"root","children":[{"type":"block","children":[{"type":"paragraph","position":{"start":{"line":3,"column":1},"end":{"line":3,"column":1}},"children":[{"type":"text","value":"This part of the book looks at how text editors can support a Git-based workflow without replacing the underlying Git concepts.","position":{"start":{"line":3,"column":1},"end":{"line":3,"column":1}},"key":"M0zgodyGYp"}],"key":"JHIgH6yxrx"},{"type":"paragraph","position":{"start":{"line":5,"column":1},"end":{"line":5,"column":1}},"children":[{"type":"text","value":"The chapters in this section provide an overview of editor integration and a more detailed walkthrough for Visual Studio Code.","position":{"start":{"line":5,"column":1},"end":{"line":5,"column":1}},"key":"WgsbVjoQHM"}],"key":"XjrGTZJhir"}],"key":"HmYk0rn133"}],"key":"Qn0gy57uAR"},"references":{"cite":{"order":[],"data":{}}},"footer":{"navigation":{"prev":{"title":"Virtual Environments","url":"/virt-env","group":"Git and GitHub Use, Collaboration, and Workflow"},"next":{"title":"Text Editors and Git Overview","url":"/texteditorsintro","group":"Git and GitHub Use, Collaboration, and Workflow"}}},"domain":"http://localhost:3000"}