{"version":3,"kind":"Article","sha256":"59e25c647e32ef389d081b6fb8d2807346bae5219f171ccf9ccc6fd03edb5b4b","slug":"index-5","location":"/content/appendix/index.md","dependencies":[],"frontmatter":{"title":"Appendix","content_includes_title":false,"authors":[{"nameParsed":{"literal":"Richard W. Evans","given":"Richard W.","family":"Evans"},"name":"Richard W. Evans","id":"contributors-myst-generated-uid-0"},{"nameParsed":{"literal":"Jason DeBacker","given":"Jason","family":"DeBacker"},"name":"Jason DeBacker","id":"contributors-myst-generated-uid-1"}],"github":"https://github.com/PSLmodels/Git-Tutorial","numbering":{"title":{"enabled":true}},"source_url":"https://github.com/PSLmodels/Git-Tutorial/blob/main/book/content/appendix/index.md","edit_url":"https://github.com/PSLmodels/Git-Tutorial/edit/main/book/content/appendix/index.md","enumerator":"5","exports":[{"format":"md","filename":"index.md","url":"/Git-Tutorial/build/index-f948fe97c20c3d2fd3341481dda26516.md"}]},"mdast":{"type":"root","children":[{"type":"block","children":[{"type":"paragraph","position":{"start":{"line":3,"column":1},"end":{"line":3,"column":1}},"children":[{"type":"text","value":"This appendix collects reference material that supports the main tutorial.","position":{"start":{"line":3,"column":1},"end":{"line":3,"column":1}},"key":"iklK2NNV0T"}],"key":"eP9TXVRC8W"},{"type":"paragraph","position":{"start":{"line":5,"column":1},"end":{"line":5,"column":1}},"children":[{"type":"text","value":"It currently includes the glossary.","position":{"start":{"line":5,"column":1},"end":{"line":5,"column":1}},"key":"kdbpLKt6E4"}],"key":"hpW2tzrmGm"}],"key":"H8t5NOuski"}],"key":"fotjvcpa9B"},"references":{"cite":{"order":[],"data":{}}},"footer":{"navigation":{"prev":{"title":"VS Code Git Configuration","url":"/vscode","group":"Git and GitHub Use, Collaboration, and Workflow"},"next":{"title":"Glossary","url":"/glossary","group":"Git and GitHub Use, Collaboration, and Workflow"}}},"domain":"http://localhost:3000"}